mawaqit_alexa/__init__.py
mawaqit_alexa/data_provider/__init__.py
mawaqit_alexa/data_provider/csv_mawaqit_provider.py
mawaqit_alexa/data_provider/mawaqit_provider.py
mawaqit_alexa/data_provider/scraping_mawaqit_provider.py
mawaqit_alexa/exceptions/__init__.py
mawaqit_alexa/exceptions/missing_param_exception.py
mawaqit_alexa/exceptions/scraping_exception.py
mawaqit_alexa/models/__init__.py
mawaqit_alexa/models/types.py
mawaqit_alexa/services/__init__.py
mawaqit_alexa/services/calendar_generator.py
mawaqit_alexa/util/__init__.py
mawaqit_alexa/util/ttl_cache.py
mawaqit_alexa/util/util.py
mawaqit_alexa-1.0.6.dist-info/licenses/LICENSE
mawaqit_alexa-1.0.6.dist-info/METADATA
mawaqit_alexa-1.0.6.dist-info/WHEEL
mawaqit_alexa-1.0.6.dist-info/top_level.txt
mawaqit_alexa-1.0.6.dist-info/RECORD
