Metadata-Version: 2.4
Name: mawaqit-alexa
Version: 1.0.6
Summary: A simple mawaqit scraper for creating Calendar events and Alexa integration.
Home-page: https://github.com/Ahmad-Said/mawaqit_alexa
Author: Ahmad SAID
Author-email: hunter.sc.dark@gmail.com
License: MIT
Keywords: mawaqit,prayer times,icalendar,alexa,mosque,salat,calendar
Classifier: Development Status :: 4 - Beta
Classifier: Intended Audience :: Developers
Classifier: License :: OSI Approved :: MIT License
Classifier: Programming Language :: Python :: 3
Classifier: Programming Language :: Python :: 3 :: Only
Requires-Python: >=3.7
License-File: LICENSE
Requires-Dist: icalendar
Requires-Dist: requests
Requires-Dist: beautifulsoup4
Requires-Dist: typing_extensions
Dynamic: license-file
